graph_asp-0.0.9.dist-info/DESCRIPTION.rst
graph_asp-0.0.9.dist-info/METADATA
graph_asp-0.0.9.dist-info/RECORD
graph_asp-0.0.9.dist-info/WHEEL
graph_asp-0.0.9.dist-info/entry_points.txt
graph_asp-0.0.9.dist-info/metadata.json
graph_asp-0.0.9.dist-info/top_level.txt
grasp/__init__.py
grasp/__main__.py
grasp/asp.py
grasp/build_graph.py
grasp/cli.py
grasp/commons.py
grasp/extract_links.py
grasp/info.py
grasp/routines.py
