Metadata-Version: 2.0
Name: graph-asp
Version: 0.0.9
Summary: CLI endpoint to handle (ASP encoded) graphs
Home-page: https://github.com/aluriak/grasp
Author: Lucas Bourneuf
Author-email: lucas.bourneuf@laposte.net
License: GPL
Keywords: graph,Answer Set Programming
Platform: UNKNOWN
Classifier: Development Status :: 4 - Beta
Classifier: Intended Audience :: Developers
Classifier: Programming Language :: Python :: 3
Classifier: Programming Language :: Python :: 3.5
Requires-Dist: clyngor (>=0.3.1)
Requires-Dist: networkx (==2.1)
Requires-Dist: pydot (==1.2.4)
